Workbook

Sheet 销售数据明细
A1: 2024年电商销售数据明细
A2: 订单ID | B2: 订单日期 | C2: 店铺名称 | D2: 商品分类 | E2: 商品名称 | F2: 销售数量 | G2: 单价(元) | H2: 销售金额(元) | I2: 成本金额(元) | J2: 利润(元) | K2: 利润率
A3: ORD000001 | B3: 45364 | C3: 折扣专营店 | D3: 美妆个护 | E3: 沐浴露 | F3: 8 | G3: 4943 | H3: =F3*G3 | I3: =H3*0.32 | J3: =H3-I3 | K3: =IFERROR(J3/H3,0)
A4: ORD000002 | B4: 45628 | C4: 跨境电商店 | D4: 美妆个护 | E4: 面膜 | F4: 2 | G4: 1670.19 | H4: =F4*G4 | I4: =H4*0.36 | J4: =H4-I4 | K4: =IFERROR(J4/H4,0)
A5: ORD000003 | B5: 45368 | C5: 折扣专营店 | D5: 食品生鲜 | E5: 牛奶 | F5: 5 | G5: 2435.99 | H5: =F5*G5 | I5: =H5*0.65 | J5: =H5-I5 | K5: =IFERROR(J5/H5,0)
A6: ORD000004 | B6: 45380 | C6: 品牌专卖店 | D6: 家居生活 | E6: 保温杯 | F6: 2 | G6: 2184.41 | H6: =F6*G6 | I6: =H6*0.36 | J6: =H6-I6 | K6: =IFERROR(J6/H6,0)
A7: ORD000005 | B7: 45328 | C7: 官方旗舰店 | D7: 服饰鞋包 | E7: 连衣裙 | F7: 2 | G7: 929.79 | H7: =F7*G7 | I7: =H7*0.5 | J7: =H7-I7 | K7: =IFERROR(J7/H7,0)
A8: ORD000006 | B8: 45460 | C8: 跨境电商店 | D8: 服饰鞋包 | E8: 休闲卫衣 | F8: 2 | G8: 2997.34 | H8: =F8*G8 | I8: =H8*0.62 | J8: =H8-I8 | K8: =IFERROR(J8/H8,0)
A9: ORD000007 | B9: 45351 | C9: 跨境电商店 | D9: 家居生活 | E9: 收纳箱 | F9: 9 | G9: 3900.45 | H9: =F9*G9 | I9: =H9*0.65 | J9: =H9-I9 | K9: =IFERROR(J9/H9,0)
A10: ORD000008 | B10: 45371 | C10: 官方旗舰店 | D10: 家居生活 | E10: 空气净化器 | F10: 1 | G10: 3717.06 | H10: =F10*G10 | I10: =H10*0.58 | J10: =H10-I10 | K10: =IFERROR(J10/H10,0)
A11: ORD000009 | B11: 45517 | C11: 跨境电商店 | D11: 3C数码 | E11: 平板电脑 | F11: 5 | G11: 2825.38 | H11: =F11*G11 | I11: =H11*0.43 | J11: =H11-I11 | K11: =IFERROR(J11/H11,0)
A12: ORD000010 | B12: 45356 | C12: 品牌专卖店 | D12: 家居生活 | E12: 床上四件套 | F12: 3 | G12: 2182.09 | H12: =F12*G12 | I12: =H12*0.68 | J12: =H12-I12 | K12: =IFERROR(J12/H12,0)
A13: ORD000011 | B13: 45635 | C13: 跨境电商店 | D13: 食品生鲜 | E13: 肉类生鲜 | F13: 10 | G13: 764.7 | H13: =F13*G13 | I13: =H13*0.36 | J13: =H13-I13 | K13: =IFERROR(J13/H13,0)
A14: ORD000012 | B14: 45345 | C14: 品牌专卖店 | D14: 3C数码 | E14: 智能手表 | F14: 1 | G14: 1571.88 | H14: =F14*G14 | I14: =H14*0.56 | J14: =H14-I14 | K14: =IFERROR(J14/H14,0)
A15: ORD000013 | B15: 45656 | C15: 品牌专卖店 | D15: 3C数码 | E15: 智能手机 | F15: 8 | G15: 2997.43 | H15: =F15*G15 | I15: =H15*0.68 | J15: =H15-I15 | K15: =IFERROR(J15/H15,0)
A16: ORD000014 | B16: 45388 | C16: 品牌专卖店 | D16: 家居生活 | E16: 空气净化器 | F16: 4 | G16: 248.96 | H16: =F16*G16 | I16: =H16*0.66 | J16: =H16-I16 | K16: =IFERROR(J16/H16,0)
A17: ORD000015 | B17: 45589 | C17: 折扣专营店 | D17: 服饰鞋包 | E17: 运动鞋 | F17: 8 | G17: 2813.8 | H17: =F17*G17 | I17: =H17*0.38 | J17: =H17-I17 | K17: =IFERROR(J17/H17,0)
A18: ORD000016 | B18: 45494 | C18: 品牌专卖店 | D18: 3C数码 | E18: 平板电脑 | F18: 3 | G18: 1956.23 | H18: =F18*G18 | I18: =H18*0.68 | J18: =H18-I18 | K18: =IFERROR(J18/H18,0)
A19: ORD000017 | B19: 45358 | C19: 官方旗舰店 | D19: 食品生鲜 | E19: 肉类生鲜 | F19: 9 | G19: 408.56 | H19: =F19*G19 | I19: =H19*0.68 | J19: =H19-I19 | K19: =IFERROR(J19/H19,0)
A20: ORD000018 | B20: 45461 | C20: 折扣专营店 | D20: 家居生活 | E20: 保温杯 | F20: 3 | G20: 1531.4 | H20: =F20*G20 | I20: =H20*0.38 | J20: =H20-I20 | K20: =IFERROR(J20/H20,0)
A21: ORD000019 | B21: 45478 | C21: 跨境电商店 | D21: 3C数码 | E21: 笔记本电脑 | F21: 8 | G21: 873.05 | H21: =F21*G21 | I21: =H21*0.44 | J21: =H21-I21 | K21: =IFERROR(J21/H21,0)
A22: ORD000020 | B22: 45566 | C22: 折扣专营店 | D22: 美妆个护 | E22: 洗发水 | F22: 8 | G22: 4180.37 | H22: =F22*G22 | I22: =H22*0.48 | J22: =H22-I22 | K22: =IFERROR(J22/H22,0)
A23: ORD000021 | B23: 45547 | C23: 折扣专营店 | D23: 美妆个护 | E23: 粉底液 | F23: 9 | G23: 127.92 | H23: =F23*G23 | I23: =H23*0.33 | J23: =H23-I23 | K23: =IFERROR(J23/H23,0)
A24: ORD000022 | B24: 45483 | C24: 跨境电商店 | D24: 3C数码 | E24: 平板电脑 | F24: 4 | G24: 1194.65 | H24: =F24*G24 | I24: =H24*0.58 | J24: =H24-I24 | K24: =IFERROR(J24/H24,0)
A25: ORD000023 | B25: 45641 | C25: 品牌专卖店 | D25: 3C数码 | E25: 智能手表 | F25: 7 | G25: 3730.78 | H25: =F25*G25 | I25: =H25*0.31 | J25: =H25-I25 | K25: =IFERROR(J25/H25,0)
A26: ORD000024 | B26: 45314 | C26: 折扣专营店 | D26: 3C数码 | E26: 笔记本电脑 | F26: 10 | G26: 3708.02 | H26: =F26*G26 | I26: =H26*0.49 | J26: =H26-I26 | K26: =IFERROR(J26/H26,0)
A27: ORD000025 | B27: 45586 | C27: 官方旗舰店 | D27: 家居生活 | E27: 扫地机器人 | F27: 10 | G27: 4168.12 | H27: =F27*G27 | I27: =H27*0.46 | J27: =H27-I27 | K27: =IFERROR(J27/H27,0)
A28: ORD000026 | B28: 45340 | C28: 官方旗舰店 | D28: 服饰鞋包 | E28: 牛仔裤 | F28: 4 | G28: 4143.81 | H28: =F28*G28 | I28: =H28*0.46 | J28: =H28-I28 | K28: =IFERROR(J28/H28,0)
A29: ORD000027 | B29: 45544 | C29: 折扣专营店 | D29: 3C数码 | E29: 笔记本电脑 | F29: 8 | G29: 1419.36 | H29: =F29*G29 | I29: =H29*0.45 | J29: =H29-I29 | K29: =IFERROR(J29/H29,0)
A30: ORD000028 | B30: 45657 | C30: 官方旗舰店 | D30: 家居生活 | E30: 床上四件套 | F30: 1 | G30: 865.32 | H30: =F30*G30 | I30: =H30*0.46 | J30: =H30-I30 | K30: =IFERROR(J30/H30,0)
A31: ORD000029 | B31: 45450 | C31: 折扣专营店 | D31: 家居生活 | E31: 床上四件套 | F31: 4 | G31: 3452.79 | H31: =F31*G31 | I31: =H31*0.7 | J31: =H31-I31 | K31: =IFERROR(J31/H31,0)
A32: ORD000030 | B32: 45406 | C32: 折扣专营店 | D32: 3C数码 | E32: 平板电脑 | F32: 3 | G32: 4684.88 | H32: =F32*G32 | I32: =H32*0.57 | J32: =H32-I32 | K32: =IFERROR(J32/H32,0)
A33: ORD000031 | B33: 45445 | C33: 跨境电商店 | D33: 3C数码 | E33: 笔记本电脑 | F33: 3 | G33: 1514.8 | H33: =F33*G33 | I33: =H33*0.51 | J33: =H33-I33 | K33: =IFERROR(J33/H33,0)
A34: ORD000032 | B34: 45321 | C34: 折扣专营店 | D34: 食品生鲜 | E34: 牛奶 | F34: 5 | G34: 2455.55 | H34: =F34*G34 | I34: =H34*0.49 | J34: =H34-I34 | K34: =IFERROR(J34/H34,0)
A35: ORD000033 | B35: 45638 | C35: 折扣专营店 | D35: 家居生活 | E35: 空气净化器 | F35: 8 | G35: 732.56 | H35: =F35*G35 | I35: =H35*0.4 | J35: =H35-I35 | K35: =IFERROR(J35/H35,0)
A36: ORD000034 | B36: 45528 | C36: 跨境电商店 | D36: 美妆个护 | E36: 面膜 | F36: 5 | G36: 1182.88 | H36: =F36*G36 | I36: =H36*0.54 | J36: =H36-I36 | K36: =IFERROR(J36/H36,0)
A37: ORD000035 | B37: 45408 | C37: 折扣专营店 | D37: 服饰鞋包 | E37: 单肩包 | F37: 10 | G37: 3775.82 | H37: =F37*G37 | I37: =H37*0.42 | J37: =H37-I37 | K37: =IFERROR(J37/H37,0)
A38: ORD000036 | B38: 45407 | C38: 跨境电商店 | D38: 美妆个护 | E38: 沐浴露 | F38: 4 | G38: 4450.29 | H38: =F38*G38 | I38: =H38*0.31 | J38: =H38-I38 | K38: =IFERROR(J38/H38,0)
A39: ORD000037 | B39: 45406 | C39: 跨境电商店 | D39: 3C数码 | E39: 无线耳机 | F39: 7 | G39: 3445.62 | H39: =F39*G39 | I39: =H39*0.4 | J39: =H39-I39 | K39: =IFERROR(J39/H39,0)
A40: ORD000038 | B40: 45485 | C40: 品牌专卖店 | D40: 家居生活 | E40: 扫地机器人 | F40: 2 | G40: 479.14 | H40: =F40*G40 | I40: =H40*0.44 | J40: =H40-I40 | K40: =IFERROR(J40/H40,0)
A41: ORD000039 | B41: 45343 | C41: 跨境电商店 | D41: 家居生活 | E41: 空气净化器 | F41: 8 | G41: 34.48 | H41: =F41*G41 | I41: =H41*0.5 | J41: =H41-I41 | K41: =IFERROR(J41/H41,0)
A42: ORD000040 | B42: 45640 | C42: 折扣专营店 | D42: 3C数码 | E42: 无线耳机 | F42: 3 | G42: 4372.16 | H42: =F42*G42 | I42: =H42*0.41 | J42: =H42-I42 | K42: =IFERROR(J42/H42,0)
A43: ORD000041 | B43: 45505 | C43: 折扣专营店 | D43: 食品生鲜 | E43: 肉类生鲜 | F43: 2 | G43: 4296.81 | H43: =F43*G43 | I43: =H43*0.36 | J43: =H43-I43 | K43: =IFERROR(J43/H43,0)
A44: ORD000042 | B44: 45440 | C44: 官方旗舰店 | D44: 食品生鲜 | E44: 肉类生鲜 | F44: 4 | G44: 681.79 | H44: =F44*G44 | I44: =H44*0.31 | J44: =H44-I44 | K44: =IFERROR(J44/H44,0)
A45: ORD000043 | B45: 45619 | C45: 跨境电商店 | D45: 服饰鞋包 | E45: 运动鞋 | F45: 1 | G45: 4827.77 | H45: =F45*G45 | I45: =H45*0.56 | J45: =H45-I45 | K45: =IFERROR(J45/H45,0)
A46: ORD000044 | B46: 45311 | C46: 折扣专营店 | D46: 3C数码 | E46: 笔记本电脑 | F46: 8 | G46: 3379.17 | H46: =F46*G46 | I46: =H46*0.53 | J46: =H46-I46 | K46: =IFERROR(J46/H46,0)
A47: ORD000045 | B47: 45514 | C47: 官方旗舰店 | D47: 服饰鞋包 | E47: 牛仔裤 | F47: 10 | G47: 2723.7 | H47: =F47*G47 | I47: =H47*0.46 | J47: =H47-I47 | K47: =IFERROR(J47/H47,0)
A48: ORD000046 | B48: 45625 | C48: 折扣专营店 | D48: 家居生活 | E48: 收纳箱 | F48: 6 | G48: 3753.37 | H48: =F48*G48 | I48: =H48*0.65 | J48: =H48-I48 | K48: =IFERROR(J48/H48,0)
A49: ORD000047 | B49: 45521 | C49: 跨境电商店 | D49: 3C数码 | E49: 智能手表 | F49: 10 | G49: 3861.02 | H49: =F49*G49 | I49: =H49*0.38 | J49: =H49-I49 | K49: =IFERROR(J49/H49,0)
A50: ORD000048 | B50: 45294 | C50: 官方旗舰店 | D50: 美妆个护 | E50: 口红 | F50: 4 | G50: 767.15 | H50: =F50*G50 | I50: =H50*0.4 | J50: =H50-I50 | K50: =IFERROR(J50/H50,0)
A51: ORD000049 | B51: 45293 | C51: 折扣专营店 | D51: 食品生鲜 | E51: 坚果礼盒 | F51: 6 | G51: 1080.46 | H51: =F51*G51 | I51: =H51*0.66 | J51: =H51-I51 | K51: =IFERROR(J51/H51,0)
A52: ORD000050 | B52: 45449 | C52: 官方旗舰店 | D52: 3C数码 | E52: 智能手机 | F52: 4 | G52: 3808.95 | H52: =F52*G52 | I52: =H52*0.68 | J52: =H52-I52 | K52: =IFERROR(J52/H52,0)
A53: ORD000051 | B53: 45362 | C53: 折扣专营店 | D53: 服饰鞋包 | E53: 休闲卫衣 | F53: 10 | G53: 3072.08 | H53: =F53*G53 | I53: =H53*0.69 | J53: =H53-I53 | K53: =IFERROR(J53/H53,0)
A54: ORD000052 | B54: 45372 | C54: 折扣专营店 | D54: 3C数码 | E54: 智能手表 | F54: 7 | G54: 171.1 | H54: =F54*G54 | I54: =H54*0.32 | J54: =H54-I54 | K54: =IFERROR(J54/H54,0)
A55: ORD000053 | B55: 45482 | C55: 跨境电商店 | D55: 服饰鞋包 | E55: 休闲卫衣 | F55: 1 | G55: 1442.74 | H55: =F55*G55 | I55: =H55*0.6 | J55: =H55-I55 | K55: =IFERROR(J55/H55,0)
A56: ORD000054 | B56: 45505 | C56: 官方旗舰店 | D56: 家居生活 | E56: 床上四件套 | F56: 7 | G56: 146.21 | H56: =F56*G56 | I56: =H56*0.52 | J56: =H56-I56 | K56: =IFERROR(J56/H56,0)
A57: ORD000055 | B57: 45358 | C57: 品牌专卖店 | D57: 食品生鲜 | E57: 水果礼盒 | F57: 2 | G57: 999.86 | H57: =F57*G57 | I57: =H57*0.67 | J57: =H57-I57 | K57: =IFERROR(J57/H57,0)
A58: ORD000056 | B58: 45362 | C58: 官方旗舰店 | D58: 3C数码 | E58: 笔记本电脑 | F58: 4 | G58: 982.56 | H58: =F58*G58 | I58: =H58*0.46 | J58: =H58-I58 | K58: =IFERROR(J58/H58,0)
A59: ORD000057 | B59: 45317 | C59: 官方旗舰店 | D59: 3C数码 | E59: 智能手机 | F59: 10 | G59: 732.04 | H59: =F59*G59 | I59: =H59*0.44 | J59: =H59-I59 | K59: =IFERROR(J59/H59,0)
A60: ORD000058 | B60: 45372 | C60: 跨境电商店 | D60: 3C数码 | E60: 智能手表 | F60: 8 | G60: 641.13 | H60: =F60*G60 | I60: =H60*0.35 | J60: =H60-I60 | K60: =IFERROR(J60/H60,0)
A61: ORD000059 | B61: 45616 | C61: 品牌专卖店 | D61: 食品生鲜 | E61: 零食大礼包 | F61: 6 | G61: 2438.23 | H61: =F61*G61 | I61: =H61*0.62 | J61: =H61-I61 | K61: =IFERROR(J61/H61,0)
A62: ORD000060 | B62: 45453 | C62: 跨境电商店 | D62: 3C数码 | E62: 笔记本电脑 | F62: 6 | G62: 2065.34 | H62: =F62*G62 | I62: =H62*0.38 | J62: =H62-I62 | K62: =IFERROR(J62/H62,0)
A63: ORD000061 | B63: 45443 | C63: 官方旗舰店 | D63: 服饰鞋包 | E63: 连衣裙 | F63: 1 | G63: 429.87 | H63: =F63*G63 | I63: =H63*0.36 | J63: =H63-I63 | K63: =IFERROR(J63/H63,0)
A64: ORD000062 | B64: 45372 | C64: 折扣专营店 | D64: 服饰鞋包 | E64: 休闲卫衣 | F64: 10 | G64: 4157.88 | H64: =F64*G64 | I64: =H64*0.39 | J64: =H64-I64 | K64: =IFERROR(J64/H64,0)
A65: ORD000063 | B65: 45309 | C65: 跨境电商店 | D65: 食品生鲜 | E65: 零食大礼包 | F65: 2 | G65: 770.98 | H65: =F65*G65 | I65: =H65*0.68 | J65: =H65-I65 | K65: =IFERROR(J65/H65,0)
A66: ORD000064 | B66: 45536 | C66: 品牌专卖店 | D66: 家居生活 | E66: 收纳箱 | F66: 10 | G66: 3692.65 | H66: =F66*G66 | I66: =H66*0.59 | J66: =H66-I66 | K66: =IFERROR(J66/H66,0)
A67: ORD000065 | B67: 45316 | C67: 品牌专卖店 | D67: 服饰鞋包 | E67: 运动鞋 | F67: 1 | G67: 3408.74 | H67: =F67*G67 | I67: =H67*0.5 | J67: =H67-I67 | K67: =IFERROR(J67/H67,0)
A68: ORD000066 | B68: 45488 | C68: 折扣专营店 | D68: 家居生活 | E68: 空气净化器 | F68: 10 | G68: 3306.99 | H68: =F68*G68 | I68: =H68*0.54 | J68: =H68-I68 | K68: =IFERROR(J68/H68,0)
A69: ORD000067 | B69: 45460 | C69: 跨境电商店 | D69: 3C数码 | E69: 笔记本电脑 | F69: 6 | G69: 1713.55 | H69: =F69*G69 | I69: =H69*0.69 | J69: =H69-I69 | K69: =IFERROR(J69/H69,0)
A70: ORD000068 | B70: 45564 | C70: 官方旗舰店 | D70: 家居生活 | E70: 床上四件套 | F70: 8 | G70: 2743.86 | H70: =F70*G70 | I70: =H70*0.63 | J70: =H70-I70 | K70: =IFERROR(J70/H70,0)
A71: ORD000069 | B71: 45432 | C71: 官方旗舰店 | D71: 3C数码 | E71: 平板电脑 | F71: 8 | G71: 2905.38 | H71: =F71*G71 | I71: =H71*0.44 | J71: =H71-I71 | K71: =IFERROR(J71/H71,0)
A72: ORD000070 | B72: 45629 | C72: 品牌专卖店 | D72: 3C数码 | E72: 智能手表 | F72: 9 | G72: 914.34 | H72: =F72*G72 | I72: =H72*0.46 | J72: =H72-I72 | K72: =IFERROR(J72/H72,0)
A73: ORD000071 | B73: 45533 | C73: 折扣专营店 | D73: 美妆个护 | E73: 面膜 | F73: 2 | G73: 2185.1 | H73: =F73*G73 | I73: =H73*0.62 | J73: =H73-I73 | K73: =IFERROR(J73/H73,0)
A74: ORD000072 | B74: 45418 | C74: 跨境电商店 | D74: 美妆个护 | E74: 粉底液 | F74: 10 | G74: 2017.24 | H74: =F74*G74 | I74: =H74*0.4 | J74: =H74-I74 | K74: =IFERROR(J74/H74,0)
A75: ORD000073 | B75: 45583 | C75: 品牌专卖店 | D75: 美妆个护 | E75: 沐浴露 | F75: 3 | G75: 3369.32 | H75: =F75*G75 | I75: =H75*0.54 | J75: =H75-I75 | K75: =IFERROR(J75/H75,0)
A76: ORD000074 | B76: 45588 | C76: 跨境电商店 | D76: 3C数码 | E76: 笔记本电脑 | F76: 10 | G76: 2350.11 | H76: =F76*G76 | I76: =H76*0.55 | J76: =H76-I76 | K76: =IFERROR(J76/H76,0)
A77: ORD000075 | B77: 45391 | C77: 官方旗舰店 | D77: 美妆个护 | E77: 口红 | F77: 9 | G77: 2733.41 | H77: =F77*G77 | I77: =H77*0.62 | J77: =H77-I77 | K77: =IFERROR(J77/H77,0)
A78: ORD000076 | B78: 45611 | C78: 官方旗舰店 | D78: 3C数码 | E78: 无线耳机 | F78: 8 | G78: 1096.33 | H78: =F78*G78 | I78: =H78*0.37 | J78: =H78-I78 | K78: =IFERROR(J78/H78,0)
A79: ORD000077 | B79: 45654 | C79: 跨境电商店 | D79: 3C数码 | E79: 笔记本电脑 | F79: 3 | G79: 2882.02 | H79: =F79*G79 | I79: =H79*0.56 | J79: =H79-I79 | K79: =IFERROR(J79/H79,0)
A80: ORD000078 | B80: 45481 | C80: 折扣专营店 | D80: 服饰鞋包 | E80: 单肩包 | F80: 5 | G80: 3242.98 | H80: =F80*G80 | I80: =H80*0.6 | J80: =H80-I80 | K80: =IFERROR(J80/H80,0)
A81: ORD000079 | B81: 45500 | C81: 折扣专营店 | D81: 服饰鞋包 | E81: 休闲卫衣 | F81: 9 | G81: 2480.73 | H81: =F81*G81 | I81: =H81*0.67 | J81: =H81-I81 | K81: =IFERROR(J81/H81,0)
A82: ORD000080 | B82: 45456 | C82: 品牌专卖店 | D82: 3C数码 | E82: 智能手表 | F82: 6 | G82: 1552.95 | H82: =F82*G82 | I82: =H82*0.37 | J82: =H82-I82 | K82: =IFERROR(J82/H82,0)
A83: ORD000081 | B83: 45318 | C83: 跨境电商店 | D83: 美妆个护 | E83: 面膜 | F83: 9 | G83: 4623.08 | H83: =F83*G83 | I83: =H83*0.58 | J83: =H83-I83 | K83: =IFERROR(J83/H83,0)
A84: ORD000082 | B84: 45451 | C84: 跨境电商店 | D84: 3C数码 | E84: 智能手表 | F84: 7 | G84: 1082.2 | H84: =F84*G84 | I84: =H84*0.59 | J84: =H84-I84 | K84: =IFERROR(J84/H84,0)
A85: ORD000083 | B85: 45474 | C85: 官方旗舰店 | D85: 家居生活 | E85: 扫地机器人 | F85: 8 | G85: 340.53 | H85: =F85*G85 | I85: =H85*0.33 | J85: =H85-I85 | K85: =IFERROR(J85/H85,0)
A86: ORD000084 | B86: 45358 | C86: 跨境电商店 | D86: 美妆个护 | E86: 沐浴露 | F86: 6 | G86: 4873.73 | H86: =F86*G86 | I86: =H86*0.43 | J86: =H86-I86 | K86: =IFERROR(J86/H86,0)
A87: ORD000085 | B87: 45539 | C87: 跨境电商店 | D87: 美妆个护 | E87: 粉底液 | F87: 9 | G87: 4397.45 | H87: =F87*G87 | I87: =H87*0.65 | J87: =H87-I87 | K87: =IFERROR(J87/H87,0)
A88: ORD000086 | B88: 45426 | C88: 跨境电商店 | D88: 食品生鲜 | E88: 坚果礼盒 | F88: 6 | G88: 4982.13 | H88: =F88*G88 | I88: =H88*0.34 | J88: =H88-I88 | K88: =IFERROR(J88/H88,0)
A89: ORD000087 | B89: 45578 | C89: 跨境电商店 | D89: 家居生活 | E89: 空气净化器 | F89: 6 | G89: 1219.35 | H89: =F89*G89 | I89: =H89*0.43 | J89: =H89-I89 | K89: =IFERROR(J89/H89,0)
A90: ORD000088 | B90: 45293 | C90: 折扣专营店 | D90: 美妆个护 | E90: 面膜 | F90: 6 | G90: 4497.85 | H90: =F90*G90 | I90: =H90*0.55 | J90: =H90-I90 | K90: =IFERROR(J90/H90,0)
A91: ORD000089 | B91: 45597 | C91: 折扣专营店 | D91: 美妆个护 | E91: 口红 | F91: 5 | G91: 4870.13 | H91: =F91*G91 | I91: =H91*0.61 | J91: =H91-I91 | K91: =IFERROR(J91/H91,0)
A92: ORD000090 | B92: 45608 | C92: 官方旗舰店 | D92: 食品生鲜 | E92: 水果礼盒 | F92: 6 | G92: 712.09 | H92: =F92*G92 | I92: =H92*0.37 | J92: =H92-I92 | K92: =IFERROR(J92/H92,0)
A93: ORD000091 | B93: 45504 | C93: 官方旗舰店 | D93: 服饰鞋包 | E93: 运动鞋 | F93: 2 | G93: 3601.34 | H93: =F93*G93 | I93: =H93*0.37 | J93: =H93-I93 | K93: =IFERROR(J93/H93,0)
A94: ORD000092 | B94: 45615 | C94: 跨境电商店 | D94: 家居生活 | E94: 床上四件套 | F94: 2 | G94: 4994.54 | H94: =F94*G94 | I94: =H94*0.47 | J94: =H94-I94 | K94: =IFERROR(J94/H94,0)
A95: ORD000093 | B95: 45540 | C95: 跨境电商店 | D95: 美妆个护 | E95: 洗发水 | F95: 4 | G95: 3145.72 | H95: =F95*G95 | I95: =H95*0.42 | J95: =H95-I95 | K95: =IFERROR(J95/H95,0)
A96: ORD000094 | B96: 45460 | C96: 跨境电商店 | D96: 服饰鞋包 | E96: 单肩包 | F96: 8 | G96: 4882.71 | H96: =F96*G96 | I96: =H96*0.59 | J96: =H96-I96 | K96: =IFERROR(J96/H96,0)
A97: ORD000095 | B97: 45510 | C97: 折扣专营店 | D97: 服饰鞋包 | E97: 连衣裙 | F97: 3 | G97: 3500.34 | H97: =F97*G97 | I97: =H97*0.47 | J97: =H97-I97 | K97: =IFERROR(J97/H97,0)
A98: ORD000096 | B98: 45415 | C98: 官方旗舰店 | D98: 服饰鞋包 | E98: 连衣裙 | F98: 7 | G98: 1169.32 | H98: =F98*G98 | I98: =H98*0.55 | J98: =H98-I98 | K98: =IFERROR(J98/H98,0)
A99: ORD000097 | B99: 45594 | C99: 品牌专卖店 | D99: 美妆个护 | E99: 面膜 | F99: 9 | G99: 3600.22 | H99: =F99*G99 | I99: =H99*0.57 | J99: =H99-I99 | K99: =IFERROR(J99/H99,0)
A100: ORD000098 | B100: 45505 | C100: 跨境电商店 | D100: 美妆个护 | E100: 口红 | F100: 9 | G100: 808.6 | H100: =F100*G100 | I100: =H100*0.55 | J100: =H100-I100 | K100: =IFERROR(J100/H100,0)
...

Sheet 月度销售汇总
A1: 2024年月度销售汇总表
A2: 月份 | B2: 店铺名称 | C2: 商品分类 | D2: 总销售数量 | E2: 总销售金额(元) | F2: 总利润(元)
A3: 1月 | B3: 官方旗舰店 | C3: 3C数码 | D3: =SUMIFS('销售数据明细'!$F:$F, '销售数据明细'!$B:$B, ">="&DATE(2024,LEFT(A3,LEN(A3)-1),1), '销售数据明细'!$B:$B, "<="&EOMONTH(DATE(2024,LEFT(A3,LEN(A3)-1),1),0), '销售数据明细'!$C:$C, B3, '销售数据明细'!$D:$D, C3) | E3: =SUMIFS('销售数据明细'!$H:$H, '销售数据明细'!$B:$B, ">="&DATE(2024,LEFT(A3,LEN(A3)-1),1), '销售数据明细'!$B:$B, "<="&EOMONTH(DATE(2024,LEFT(A3,LEN(A3)-1),1),0), '销售数据明细'!$C:$C, B3, '销售数据明细'!$D:$D, C3) | F3: =SUMIFS('销售数据明细'!$J:$J, '销售数据明细'!$B:$B, ">="&DATE(2024,LEFT(A3,LEN(A3)-1),1), '销售数据明细'!$B:$B, "<="&EOMONTH(DATE(2024,LEFT(A3,LEN(A3)-1),1),0), '销售数据明细'!$C:$C, B3, '销售数据明细'!$D:$D, C3)
A4: 1月 | B4: 官方旗舰店 | C4: 家居生活 | D4: =SUMIFS('销售数据明细'!$F:$F, '销售数据明细'!$B:$B, ">="&DATE(2024,LEFT(A4,LEN(A4)-1),1), '销售数据明细'!$B:$B, "<="&EOMONTH(DATE(2024,LEFT(A4,LEN(A4)-1),1),0), '销售数据明细'!$C:$C, B4, '销售数据明细'!$D:$D, C4) | E4: =SUMIFS('销售数据明细'!$H:$H, '销售数据明细'!$B:$B, ">="&DATE(2024,LEFT(A4,LEN(A4)-1),1), '销售数据明细'!$B:$B, "<="&EOMONTH(DATE(2024,LEFT(A4,LEN(A4)-1),1),0), '销售数据明细'!$C:$C, B4, '销售数据明细'!$D:$D, C4) | F4: =SUMIFS('销售数据明细'!$J:$J, '销售数据明细'!$B:$B, ">="&DATE(2024,LEFT(A4,LEN(A4)-1),1), '销售数据明细'!$B:$B, "<="&EOMONTH(DATE(2024,LEFT(A4,LEN(A4)-1),1),0), '销售数据明细'!$C:$C, B4, '销售数据明细'!$D:$D, C4)
A5: 1月 | B5: 官方旗舰店 | C5: 服饰鞋包 | D5: =SUMIFS('销售数据明细'!$F:$F, '销售数据明细'!$B:$B, ">="&DATE(2024,LEFT(A5,LEN(A5)-1),1), '销售数据明细'!$B:$B, "<="&EOMONTH(DATE(2024,LEFT(A5,LEN(A5)-1),1),0), '销售数据明细'!$C:$C, B5, '销售数据明细'!$D:$D, C5) | E5: =SUMIFS('销售数据明细'!$H:$H, '销售数据明细'!$B:$B, ">="&DATE(2024,LEFT(A5,LEN(A5)-1),1), '销售数据明细'!$B:$B, "<="&EOMONTH(DATE(2024,LEFT(A5,LEN(A5)-1),1),0), '销售数据明细'!$C:$C, B5, '销售数据明细'!$D:$D, C5) | F5: =SUMIFS('销售数据明细'!$J:$J, '销售数据明细'!$B:$B, ">="&DATE(2024,LEFT(A5,LEN(A5)-1),1), '销售数据明细'!$B:$B, "<="&EOMONTH(DATE(2024,LEFT(A5,LEN(A5)-1),1),0), '销售数据明细'!$C:$C, B5, '销售数据明细'!$D:$D, C5)
A6: 1月 | B6: 官方旗舰店 | C6: 美妆个护 | D6: =SUMIFS('销售数据明细'!$F:$F, '销售数据明细'!$B:$B, ">="&DATE(2024,LEFT(A6,LEN(A6)-1),1), '销售数据明细'!$B:$B, "<="&EOMONTH(DATE(2024,LEFT(A6,LEN(A6)-1),1),0), '销售数据明细'!$C:$C, B6, '销售数据明细'!$D:$D, C6) | E6: =SUMIFS('销售数据明细'!$H:$H, '销售数据明细'!$B:$B, ">="&DATE(2024,LEFT(A6,LEN(A6)-1),1), '销售数据明细'!$B:$B, "<="&EOMONTH(DATE(2024,LEFT(A6,LEN(A6)-1),1),0), '销售数据明细'!$C:$C, B6, '销售数据明细'!$D:$D, C6) | F6: =SUMIFS('销售数据明细'!$J:$J, '销售数据明细'!$B:$B, ">="&DATE(2024,LEFT(A6,LEN(A6)-1),1), '销售数据明细'!$B:$B, "<="&EOMONTH(DATE(2024,LEFT(A6,LEN(A6)-1),1),0), '销售数据明细'!$C:$C, B6, '销售数据明细'!$D:$D, C6)
A7: 1月 | B7: 官方旗舰店 | C7: 食品生鲜 | D7: =SUMIFS('销售数据明细'!$F:$F, '销售数据明细'!$B:$B, ">="&DATE(2024,LEFT(A7,LEN(A7)-1),1), '销售数据明细'!$B:$B, "<="&EOMONTH(DATE(2024,LEFT(A7,LEN(A7)-1),1),0), '销售数据明细'!$C:$C, B7, '销售数据明细'!$D:$D, C7) | E7: =SUMIFS('销售数据明细'!$H:$H, '销售数据明细'!$B:$B, ">="&DATE(2024,LEFT(A7,LEN(A7)-1),1), '销售数据明细'!$B:$B, "<="&EOMONTH(DATE(2024,LEFT(A7,LEN(A7)-1),1),0), '销售数据明细'!$C:$C, B7, '销售数据明细'!$D:$D, C7) | F7: =SUMIFS('销售数据明细'!$J:$J, '销售数据明细'!$B:$B, ">="&DATE(2024,LEFT(A7,LEN(A7)-1),1), '销售数据明细'!$B:$B, "<="&EOMONTH(DATE(2024,LEFT(A7,LEN(A7)-1),1),0), '销售数据明细'!$C:$C, B7, '销售数据明细'!$D:$D, C7)
A8: 1月 | B8: 品牌专卖店 | C8: 3C数码 | D8: =SUMIFS('销售数据明细'!$F:$F, '销售数据明细'!$B:$B, ">="&DATE(2024,LEFT(A8,LEN(A8)-1),1), '销售数据明细'!$B:$B, "<="&EOMONTH(DATE(2024,LEFT(A8,LEN(A8)-1),1),0), '销售数据明细'!$C:$C, B8, '销售数据明细'!$D:$D, C8) | E8: =SUMIFS('销售数据明细'!$H:$H, '销售数据明细'!$B:$B, ">="&DATE(2024,LEFT(A8,LEN(A8)-1),1), '销售数据明细'!$B:$B, "<="&EOMONTH(DATE(2024,LEFT(A8,LEN(A8)-1),1),0), '销售数据明细'!$C:$C, B8, '销售数据明细'!$D:$D, C8) | F8: =SUMIFS('销售数据明细'!$J:$J, '销售数据明细'!$B:$B, ">="&DATE(2024,LEFT(A8,LEN(A8)-1),1), '销售数据明细'!$B:$B, "<="&EOMONTH(DATE(2024,LEFT(A8,LEN(A8)-1),1),0), '销售数据明细'!$C:$C, B8, '销售数据明细'!$D:$D, C8)
A9: 1月 | B9: 品牌专卖店 | C9: 家居生活 | D9: =SUMIFS('销售数据明细'!$F:$F, '销售数据明细'!$B:$B, ">="&DATE(2024,LEFT(A9,LEN(A9)-1),1), '销售数据明细'!$B:$B, "<="&EOMONTH(DATE(2024,LEFT(A9,LEN(A9)-1),1),0), '销售数据明细'!$C:$C, B9, '销售数据明细'!$D:$D, C9) | E9: =SUMIFS('销售数据明细'!$H:$H, '销售数据明细'!$B:$B, ">="&DATE(2024,LEFT(A9,LEN(A9)-1),1), '销售数据明细'!$B:$B, "<="&EOMONTH(DATE(2024,LEFT(A9,LEN(A9)-1),1),0), '销售数据明细'!$C:$C, B9, '销售数据明细'!$D:$D, C9) | F9: =SUMIFS('销售数据明细'!$J:$J, '销售数据明细'!$B:$B, ">="&DATE(2024,LEFT(A9,LEN(A9)-1),1), '销售数据明细'!$B:$B, "<="&EOMONTH(DATE(2024,LEFT(A9,LEN(A9)-1),1),0), '销售数据明细'!$C:$C, B9, '销售数据明细'!$D:$D, C9)
A10: 1月 | B10: 品牌专卖店 | C10: 服饰鞋包 | D10: =SUMIFS('销售数据明细'!$F:$F, '销售数据明细'!$B:$B, ">="&DATE(2024,LEFT(A10,LEN(A10)-1),1), '销售数据明细'!$B:$B, "<="&EOMONTH(DATE(2024,LEFT(A10,LEN(A10)-1),1),0), '销售数据明细'!$C:$C, B10, '销售数据明细'!$D:$D, C10) | E10: =SUMIFS('销售数据明细'!$H:$H, '销售数据明细'!$B:$B, ">="&DATE(2024,LEFT(A10,LEN(A10)-1),1), '销售数据明细'!$B:$B, "<="&EOMONTH(DATE(2024,LEFT(A10,LEN(A10)-1),1),0), '销售数据明细'!$C:$C, B10, '销售数据明细'!$D:$D, C10) | F10: =SUMIFS('销售数据明细'!$J:$J, '销售数据明细'!$B:$B, ">="&DATE(2024,LEFT(A10,LEN(A10)-1),1), '销售数据明细'!$B:$B, "<="&EOMONTH(DATE(2024,LEFT(A10,LEN(A10)-1),1),0), '销售数据明细'!$C:$C, B10, '销售数据明细'!$D:$D, C10)
A11: 1月 | B11: 品牌专卖店 | C11: 美妆个护 | D11: =SUMIFS('销售数据明细'!$F:$F, '销售数据明细'!$B:$B, ">="&DATE(2024,LEFT(A11,LEN(A11)-1),1), '销售数据明细'!$B:$B, "<="&EOMONTH(DATE(2024,LEFT(A11,LEN(A11)-1),1),0), '销售数据明细'!$C:$C, B11, '销售数据明细'!$D:$D, C11) | E11: =SUMIFS('销售数据明细'!$H:$H, '销售数据明细'!$B:$B, ">="&DATE(2024,LEFT(A11,LEN(A11)-1),1), '销售数据明细'!$B:$B, "<="&EOMONTH(DATE(2024,LEFT(A11,LEN(A11)-1),1),0), '销售数据明细'!$C:$C, B11, '销售数据明细'!$D:$D, C11) | F11: =SUMIFS('销售数据明细'!$J:$J, '销售数据明细'!$B:$B, ">="&DATE(2024,LEFT(A11,LEN(A11)-1),1), '销售数据明细'!$B:$B, "<="&EOMONTH(DATE(2024,LEFT(A11,LEN(A11)-1),1),0), '销售数据明细'!$C:$C, B11, '销售数据明细'!$D:$D, C11)
A12: 1月 | B12: 品牌专卖店 | C12: 食品生鲜 | D12: =SUMIFS('销售数据明细'!$F:$F, '销售数据明细'!$B:$B, ">="&DATE(2024,LEFT(A12,LEN(A12)-1),1), '销售数据明细'!$B:$B, "<="&EOMONTH(DATE(2024,LEFT(A12,LEN(A12)-1),1),0), '销售数据明细'!$C:$C, B12, '销售数据明细'!$D:$D, C12) | E12: =SUMIFS('销售数据明细'!$H:$H, '销售数据明细'!$B:$B, ">="&DATE(2024,LEFT(A12,LEN(A12)-1),1), '销售数据明细'!$B:$B, "<="&EOMONTH(DATE(2024,LEFT(A12,LEN(A12)-1),1),0), '销售数据明细'!$C:$C, B12, '销售数据明细'!$D:$D, C12) | F12: =SUMIFS('销售数据明细'!$J:$J, '销售数据明细'!$B:$B, ">="&DATE(2024,LEFT(A12,LEN(A12)-1),1), '销售数据明细'!$B:$B, "<="&EOMONTH(DATE(2024,LEFT(A12,LEN(A12)-1),1),0), '销售数据明细'!$C:$C, B12, '销售数据明细'!$D:$D, C12)
A13: 1月 | B13: 折扣专营店 | C13: 3C数码 | D13: =SUMIFS('销售数据明细'!$F:$F, '销售数据明细'!$B:$B, ">="&DATE(2024,LEFT(A13,LEN(A13)-1),1), '销售数据明细'!$B:$B, "<="&EOMONTH(DATE(2024,LEFT(A13,LEN(A13)-1),1),0), '销售数据明细'!$C:$C, B13, '销售数据明细'!$D:$D, C13) | E13: =SUMIFS('销售数据明细'!$H:$H, '销售数据明细'!$B:$B, ">="&DATE(2024,LEFT(A13,LEN(A13)-1),1), '销售数据明细'!$B:$B, "<="&EOMONTH(DATE(2024,LEFT(A13,LEN(A13)-1),1),0), '销售数据明细'!$C:$C, B13, '销售数据明细'!$D:$D, C13) | F13: =SUMIFS('销售数据明细'!$J:$J, '销售数据明细'!$B:$B, ">="&DATE(2024,LEFT(A13,LEN(A13)-1),1), '销售数据明细'!$B:$B, "<="&EOMONTH(DATE(2024,LEFT(A13,LEN(A13)-1),1),0), '销售数据明细'!$C:$C, B13, '销售数据明细'!$D:$D, C13)
A14: 1月 | B14: 折扣专营店 | C14: 家居生活 | D14: =SUMIFS('销售数据明细'!$F:$F, '销售数据明细'!$B:$B, ">="&DATE(2024,LEFT(A14,LEN(A14)-1),1), '销售数据明细'!$B:$B, "<="&EOMONTH(DATE(2024,LEFT(A14,LEN(A14)-1),1),0), '销售数据明细'!$C:$C, B14, '销售数据明细'!$D:$D, C14) | E14: =SUMIFS('销售数据明细'!$H:$H, '销售数据明细'!$B:$B, ">="&DATE(2024,LEFT(A14,LEN(A14)-1),1), '销售数据明细'!$B:$B, "<="&EOMONTH(DATE(2024,LEFT(A14,LEN(A14)-1),1),0), '销售数据明细'!$C:$C, B14, '销售数据明细'!$D:$D, C14) | F14: =SUMIFS('销售数据明细'!$J:$J, '销售数据明细'!$B:$B, ">="&DATE(2024,LEFT(A14,LEN(A14)-1),1), '销售数据明细'!$B:$B, "<="&EOMONTH(DATE(2024,LEFT(A14,LEN(A14)-1),1),0), '销售数据明细'!$C:$C, B14, '销售数据明细'!$D:$D, C14)
... A242: 12月 | B242: 跨境电商店 | C242: 食品生鲜 | D242: =SUMIFS('销售数据明细'!$F:$F, '销售数据明细'!$B:$B, ">="&DATE(2024,LEFT(A242,LEN(A242)-1),1), '销售数据明细'!$B:$B, "<="&EOMONTH(DATE(2024,LEFT(A242,LEN(A242)-1),1),0), '销售数据明细'!$C:$C, B242, '销售数据明细'!$D:$D, C242) | E242: =SUMIFS('销售数据明细'!$H:$H, '销售数据明细'!$B:$B, ">="&DATE(2024,LEFT(A242,LEN(A242)-1),1), '销售数据明细'!$B:$B, "<="&EOMONTH(DATE(2024,LEFT(A242,LEN(A242)-1),1),0), '销售数据明细'!$C:$C, B242, '销售数据明细'!$D:$D, C242) | F242: =SUMIFS('销售数据明细'!$J:$J, '销售数据明细'!$B:$B, ">="&DATE(2024,LEFT(A242,LEN(A242)-1),1), '销售数据明细'!$B:$B, "<="&EOMONTH(DATE(2024,LEFT(A242,LEN(A242)-1),1),0), '销售数据明细'!$C:$C, B242, '销售数据明细'!$D:$D, C242)
